pytorch_grad_cam/__init__.py
pytorch_grad_cam/ablation_cam.py
pytorch_grad_cam/ablation_cam_multilayer.py
pytorch_grad_cam/ablation_layer.py
pytorch_grad_cam/activations_and_gradients.py
pytorch_grad_cam/base_cam.py
pytorch_grad_cam/eigen_cam.py
pytorch_grad_cam/eigen_grad_cam.py
pytorch_grad_cam/feature_factorization/__init__.py
pytorch_grad_cam/feature_factorization/deep_feature_factorization.py
pytorch_grad_cam/fullgrad_cam.py
pytorch_grad_cam/grad_cam.py
pytorch_grad_cam/grad_cam_elementwise.py
pytorch_grad_cam/grad_cam_plusplus.py
pytorch_grad_cam/guided_backprop.py
pytorch_grad_cam/hirescam.py
pytorch_grad_cam/layer_cam.py
pytorch_grad_cam/metrics/__init__.py
pytorch_grad_cam/metrics/cam_mult_image.py
pytorch_grad_cam/metrics/perturbation_confidence.py
pytorch_grad_cam/metrics/road.py
pytorch_grad_cam/random_cam.py
pytorch_grad_cam/score_cam.py
pytorch_grad_cam/sobel_cam.py
pytorch_grad_cam/utils/__init__.py
pytorch_grad_cam/utils/find_layers.py
pytorch_grad_cam/utils/image.py
pytorch_grad_cam/utils/model_targets.py
pytorch_grad_cam/utils/reshape_transforms.py
pytorch_grad_cam/utils/svd_on_activations.py
pytorch_grad_cam/xgrad_cam.py
grad_cam_orobix-1.5.3.dev1.dist-info/LICENSE
grad_cam_orobix-1.5.3.dev1.dist-info/METADATA
grad_cam_orobix-1.5.3.dev1.dist-info/WHEEL
grad_cam_orobix-1.5.3.dev1.dist-info/RECORD
