Metadata-Version: 2.1
Name: grad-cam-orobix
Version: 1.5.3.dev1
Summary: Many Class Activation Map methods implemented in Pytorch. Including Grad-CAM, Grad-CAM++, Score-CAM, Ablation-CAM and XGrad-CAM
License: MIT
Author: Jacob Gildenblat
Author-email: jacob.gildenblat@gmail.com
Requires-Python: >=3.9,<3.11
Classifier: License :: OSI Approved :: MIT License
Classifier: Programming Language :: Python :: 3
Classifier: Programming Language :: Python :: 3.9
Classifier: Programming Language :: Python :: 3.10
Requires-Dist: Pillow (>=9.0.0)
Requires-Dist: matplotlib (>=3.6.0)
Requires-Dist: numpy (>=1.20.0)
Requires-Dist: opencv-python-headless (>=4.7.0.72)
Requires-Dist: scikit-learn (>=1.2.0)
Requires-Dist: torch (>=1.7.1)
Requires-Dist: torchvision (>=0.8.2)
Requires-Dist: tqdm (>=4.66.0)
Requires-Dist: ttach (>=0.0.3)
